scanner/__init__.py
scanner/__main__.py
scanner/args_parser.py
scanner/consts.py
scanner/detector.py
scanner/scan_manager.py
techackportscanner-1.0.2.dist-info/LICENSE
techackportscanner-1.0.2.dist-info/METADATA
techackportscanner-1.0.2.dist-info/WHEEL
techackportscanner-1.0.2.dist-info/top_level.txt
techackportscanner-1.0.2.dist-info/RECORD
