Metadata-Version: 2.2
Name: TecHackPortScanner
Version: 1.0.2
Summary: A simple package for scanning ports on a network.
Author-email: Lucas Hix <admin@peng1104.net>
License: Copyright © 2025 Lucas Hix <admin@peng1104.net>
Project-URL: changelog, https://github.com/Peng1104/PortScanner/releases/latest
Project-URL: issues, https://github.com/Peng1104/PortScanner/issues
Project-URL: source, https://github.com/Peng1104/PortScanner
Classifier: License :: OSI Approved :: MIT License
Classifier: Programming Language :: Python :: 3
Classifier: Programming Language :: Python :: 3 :: Only
Classifier: Programming Language :: Python :: 3.9
Classifier: Programming Language :: Python :: 3.10
Classifier: Programming Language :: Python :: 3.11
Classifier: Programming Language :: Python :: 3.12
Classifier: Programming Language :: Python :: 3.13
Classifier: License :: OSI Approved :: MIT License
Classifier: Operating System :: OS Independent
Requires-Python: >=3.9
License-File: LICENSE
Requires-Dist: scapy
